{ "compressionlevel":-1,
 "editorsettings":
    {
     "export":
        {
         "target":"."
        }
    },
 "height":8,
 "infinite":false,
 "layers":[
        {
         "data":[41, 5, 56, 16, 16, 16, 21, 252, 256, 253, 39, 246, 56, 28, 28, 49, 19, 248, 256, 253, 41, 252, 56, 28, 28, 27, 23, 5, 248, 249, 250, 256, 47, 48, 48, 48, 73, 75, 75, 74, 251, 253, 58, 59, 59, 183, 226, 183, 59, 59, 39, 248, 247, 112, 246, 247, 5, 5, 5, 5, 42, 39, 248, 254, 251, 251, 254, 247, 38, 39, 43, 42, 39, 38, 39, 38, 39, 38, 43, 42],
         "height":8,
         "id":1,
         "name":"Tiles",
         "opacity":1,
         "type":"tilelayer",
         "visible":true,
         "width":10,
         "x":0,
         "y":0
        }, 
        {
         "data":[0, 0, 0, 53, 0, 0, 0, 0, 0, 0, 0, 0, 0, 0, 0, 0, 0, 0, 0, 0, 0, 0, 0, 0, 0, 0, 0, 0, 0, 0, 39, 252, 0, 0, 0, 0, 0, 0, 0, 0, 41, 252, 0, 0, 0, 0, 0, 0, 0, 0, 0, 0, 0, 0, 0, 0, 0, 0, 0, 0, 0, 0, 0, 0, 0, 0, 0, 0, 0, 0, 0, 0, 0, 0, 0, 0, 0, 0, 0, 0],
         "height":8,
         "id":2,
         "name":"Mod",
         "opacity":1,
         "type":"tilelayer",
         "visible":true,
         "width":10,
         "x":0,
         "y":0
        }, 
        {
         "draworder":"topdown",
         "id":3,
         "name":"EntityLayer",
         "objects":[
                {
                 "height":8,
                 "id":1,
                 "name":"1:15:2f0:50:7c",
                 "rotation":0,
                 "type":"warp",
                 "visible":true,
                 "width":8,
                 "x":0,
                 "y":0
                }],
         "opacity":1,
         "type":"objectgroup",
         "visible":true,
         "x":0,
         "y":0
        }],
 "nextlayerid":1,
 "nextobjectid":2,
 "orientation":"orthogonal",
 "properties":[
        {
         "name":"animationset",
         "type":"string",
         "value":"03"
        }, 
        {
         "name":"attribset",
         "type":"string",
         "value":"22:3400"
        }, 
        {
         "name":"palette",
         "type":"string",
         "value":"0E"
        }, 
        {
         "name":"tileset",
         "type":"string",
         "value":"36"
        }],
 "renderorder":"right-down",
 "tiledversion":"1.4.3",
 "tileheight":16,
 "tilesets":[
        {
         "columns":16,
         "firstgid":1,
         "image":"tiles_36_03_0e_22_3400.png",
         "imageheight":256,
         "imagewidth":256,
         "margin":0,
         "name":"main",
         "spacing":0,
         "tilecount":256,
         "tileheight":16,
         "tilewidth":16
        }],
 "tilewidth":16,
 "type":"map",
 "version":1.4,
 "width":10
}